micropython_sht4x/__init__.py
micropython_sht4x/sht4x.py
micropython_sht4x-0.1.0.dist-info/LICENSE
micropython_sht4x-0.1.0.dist-info/METADATA
micropython_sht4x-0.1.0.dist-info/WHEEL
micropython_sht4x-0.1.0.dist-info/top_level.txt
micropython_sht4x-0.1.0.dist-info/RECORD
