Metadata-Version: 2.1
Name: micropython-sht4x
Version: 0.1.0
Summary: MicroPython Driver fot the Sensirion Temperature and Humidity SHT40 and SHT45 Sensor
Author-email: JDM <xxyx@mailmeto.mozmail.com>
License: MIT
Project-URL: Homepage, https://github.com/jposada202020/MicroPython_SHT4X
Keywords: sensor,micropython,sht4x,temperature,humidity,driver,sensirion,sht40,sht45,micropython,sensor
Classifier: Intended Audience :: Developers
Classifier: Topic :: Software Development :: Libraries
Classifier: Topic :: Software Development :: Embedded Systems
Classifier: Topic :: System :: Hardware
Classifier: License :: OSI Approved :: MIT License
Classifier: Programming Language :: Python :: Implementation :: MicroPython
License-File: LICENSE
